greads/__init__.py
greads/greads.py
greads-0.7.dist-info/entry_points.txt
greads-0.7.dist-info/LICENSE
greads-0.7.dist-info/WHEEL
greads-0.7.dist-info/METADATA
greads-0.7.dist-info/RECORD
