Metadata-Version: 2.1
Name: greads
Version: 0.7
Summary: Command-line tool to scrape quotes from Goodreads
Author-email: Alyetama <56323389+Alyetama@users.noreply.github.com>
Classifier: License :: OSI Approved :: MIT License
Requires-Dist: tqdm
Requires-Dist: langdetect~=1.0.7
Requires-Dist: requests
Requires-Dist: beautifulsoup4~=4.11.1
Project-URL: Home, https://github.com/Alyetama/goodreads-quotes
